Metadata-Version: 1.2
Name: dg-predictor
Version: 0.1.3
Summary: ForAll
Home-page: https://github.com/user/dg_predictor
Author: muzi
Author-email: muzi@gmail.com
License: MIT License
Platform: UNKNOWN
Requires-Python: >=2.7, !=3.0.*, !=3.1.*, !=3.2.*, !=3.3.*, !=3.4.*
